odoo/addons/product_cost_price_avco_sync_mrp_subcontracting/README.rst
odoo/addons/product_cost_price_avco_sync_mrp_subcontracting/__init__.py
odoo/addons/product_cost_price_avco_sync_mrp_subcontracting/__manifest__.py
odoo/addons/product_cost_price_avco_sync_mrp_subcontracting/hooks.py
odoo/addons/product_cost_price_avco_sync_mrp_subcontracting/i18n/es.po
odoo/addons/product_cost_price_avco_sync_mrp_subcontracting/i18n/product_cost_price_avco_sync_mrp_subcontracting.pot
odoo/addons/product_cost_price_avco_sync_mrp_subcontracting/models/__init__.py
odoo/addons/product_cost_price_avco_sync_mrp_subcontracting/models/stock_move.py
odoo/addons/product_cost_price_avco_sync_mrp_subcontracting/models/stock_valuation_layer.py
odoo/addons/product_cost_price_avco_sync_mrp_subcontracting/readme/CONTRIBUTORS.rst
odoo/addons/product_cost_price_avco_sync_mrp_subcontracting/readme/DESCRIPTION.rst
odoo/addons/product_cost_price_avco_sync_mrp_subcontracting/static/description/icon.png
odoo/addons/product_cost_price_avco_sync_mrp_subcontracting/static/description/index.html
odoo13_addon_product_cost_price_avco_sync_mrp_subcontracting-13.0.1.0.1.dist-info/METADATA
odoo13_addon_product_cost_price_avco_sync_mrp_subcontracting-13.0.1.0.1.dist-info/WHEEL
odoo13_addon_product_cost_price_avco_sync_mrp_subcontracting-13.0.1.0.1.dist-info/top_level.txt
odoo13_addon_product_cost_price_avco_sync_mrp_subcontracting-13.0.1.0.1.dist-info/RECORD
